ivcap_fastapi/__init__.py
ivcap_fastapi/json_rpc.py
ivcap_fastapi/logger.py
ivcap_fastapi/logging.json
ivcap_fastapi/py.typed
ivcap_fastapi/server.py
ivcap_fastapi/try_later.py
ivcap_fastapi-0.3.1.dist-info/AUTHORS.md
ivcap_fastapi-0.3.1.dist-info/LICENSE
ivcap_fastapi-0.3.1.dist-info/METADATA
ivcap_fastapi-0.3.1.dist-info/WHEEL
ivcap_fastapi-0.3.1.dist-info/RECORD
